{
  "Data": {
    "GraphInputFile": "data/cit-HepPh-new.txt",
    "GraphInputType": "NNT",
    "GraphOutputType": "NNT",
    "GraphOutputFile": "experiments/citations/graphfiles/CIT.dat",
    "Directed": false
  },
  "Action": {
    "Grow": {
      "Start": 820800000,
      "Interval": 10,
      "MaxNodes": 34343
    }
  },
  "ObjectModel": [
    {
      "Start": 810800000,
      "End": 1015956000,
      "Components": [
        {
          "ComponentName": "DegreeModelComponent",
          "Weight": 0.02
        },
        {
          "ComponentName": "TriangleClosure",
          "Weight": 0.98
        }
      ]
    }
  ],
  "OperationModel":
  {
    "Name": "Clone",
    "FileName": "experiments/citations/CitationsOpModel.feta",
    "Start": 820800000
  }
}